proofpoint_tap/__init__.py
proofpoint_tap/proofpoint_tap.py
proofpoint_tap-0.0.2.dist-info/LICENSE
proofpoint_tap-0.0.2.dist-info/METADATA
proofpoint_tap-0.0.2.dist-info/WHEEL
proofpoint_tap-0.0.2.dist-info/top_level.txt
proofpoint_tap-0.0.2.dist-info/RECORD
