Metadata-Version: 2.1
Name: proofpoint-tap
Version: 0.0.2
Summary: Proofpoint TAP API client library
Home-page: https://github.com/drizzo-tech/proofpoint_tap
Author: Mike Olden
Author-email: michael.olden@oldendigital.com
License: Apache 2.0
Project-URL: Bug Tracker, https://github.com/drizzo-tech/proofpoint_tap/issues
Keywords: Proofpoint,TAP
Platform: UNKNOWN
Classifier: Programming Language :: Python :: 3
Classifier: License :: OSI Approved :: Apache Software License
Classifier: Operating System :: OS Independent
Requires-Python: >=3.6, <4
License-File: LICENSE
Requires-Dist: requests
